avfcomp-1.4.3.dist-info/METADATA
avfcomp-1.4.3.dist-info/WHEEL
avfcomp-1.4.3.dist-info/licenses/LICENSE
avfcomp/__init__.py
avfcomp/avfcomp.egg-info/PKG-INFO
avfcomp/avfcomp.egg-info/SOURCES.txt
avfcomp/avfcomp.egg-info/dependency_links.txt
avfcomp/avfcomp.egg-info/top_level.txt
avfcomp/base.py
avfcomp/comp.py
avfcomp/config.py
avfcomp/decomp.py
avfcomp/handler.py
avfcomp-1.4.3.dist-info/RECORD
