Metadata-Version: 2.1
Name: avfcomp
Version: 1.4.2
Summary: A compression/decompression library for AVF files.
Author: Cai Li, Tony Xiang
License: MIT
Keywords: minesweeper,compression,decompression
Classifier: Development Status :: 4 - Beta
Classifier: License :: OSI Approved :: MIT License
Requires-Python: >=3.8
License-File: LICENSE
